ado_wrapper/__init__.py
ado_wrapper/__main__.py
ado_wrapper/client.py
ado_wrapper/dumps.py
ado_wrapper/errors.py
ado_wrapper/generate_docs.py
ado_wrapper/logging_session.py
ado_wrapper/resources/__init__.py
ado_wrapper/resources/agent_pools.py
ado_wrapper/resources/annotated_tags.py
ado_wrapper/resources/artifact.py
ado_wrapper/resources/audit_logs.py
ado_wrapper/resources/branches.py
ado_wrapper/resources/build_definitions.py
ado_wrapper/resources/build_timeline.py
ado_wrapper/resources/builds.py
ado_wrapper/resources/code_change.py
ado_wrapper/resources/commits.py
ado_wrapper/resources/environment.py
ado_wrapper/resources/groups.py
ado_wrapper/resources/merge_policies.py
ado_wrapper/resources/organisation_settings.py
ado_wrapper/resources/organisations.py
ado_wrapper/resources/permissions.py
ado_wrapper/resources/personal_access_tokens.py
ado_wrapper/resources/project_settings.py
ado_wrapper/resources/projects.py
ado_wrapper/resources/pull_requests.py
ado_wrapper/resources/releases.py
ado_wrapper/resources/repo.py
ado_wrapper/resources/repo_user_permission.py
ado_wrapper/resources/runs.py
ado_wrapper/resources/searches.py
ado_wrapper/resources/secure_files.py
ado_wrapper/resources/service_endpoint.py
ado_wrapper/resources/teams.py
ado_wrapper/resources/users.py
ado_wrapper/resources/variable_groups.py
ado_wrapper/resources/wikis.py
ado_wrapper/resources/work_item.py
ado_wrapper/state_managed_abc.py
ado_wrapper/state_manager.py
ado_wrapper/typing_info.py
ado_wrapper/utils.py
ado_wrapper-1.47.0.dist-info/LICENSE
ado_wrapper-1.47.0.dist-info/METADATA
ado_wrapper-1.47.0.dist-info/WHEEL
ado_wrapper-1.47.0.dist-info/entry_points.txt
ado_wrapper-1.47.0.dist-info/RECORD
