Metadata-Version: 2.1
Name: ado_wrapper
Version: 1.47.0
Summary: A high level wrapper around the AzureDevops API including OOP principals and state management
License: Proprietary
Author: Ben Skerritt
Requires-Python: >=3.10,<4.0
Classifier: License :: Other/Proprietary License
Classifier: Programming Language :: Python :: 3
Classifier: Programming Language :: Python :: 3.10
Classifier: Programming Language :: Python :: 3.11
Requires-Dist: pyyaml (==6.0.1)
Requires-Dist: requests (==2.31.0)
